pyramid_clamav/__init__.py
pyramid_clamav/locale/pyramid_clamav.pot
pyramid_clamav/locale/de_DE/LC_MESSAGES/pyramid_clamav.po
pyramid_clamav/tests/__init__.py
pyramid_clamav/tests/test_integration.py
pyramid_clamav-0.9.dist-info/METADATA
pyramid_clamav-0.9.dist-info/WHEEL
pyramid_clamav-0.9.dist-info/top_level.txt
pyramid_clamav-0.9.dist-info/RECORD
