Metadata-Version: 2.1
Name: pyramid-clamav
Version: 0.9
Summary: A tween checking file uploads for viruses using clamav.
Home-page: https://github.com/risclog-solution/pyramid_clamav
Author: ('RiscLOG Solution Gmbh',)
Author-email: info@risclog.de
License: BSD
Keywords: wsgi pylons pyramid clamav virus
Platform: UNKNOWN
Classifier: Intended Audience :: Developers
Classifier: Programming Language :: Python
Classifier: Programming Language :: Python :: 3
Classifier: Programming Language :: Python :: 3.5
Classifier: Programming Language :: Python :: 3.6
Classifier: Programming Language :: Python :: 3.7
Classifier: Framework :: Pyramid
Classifier: Topic :: Internet :: WWW/HTTP :: WSGI
Classifier: License :: Repoze Public License
Requires-Dist: pyramid (>=1.3)
Requires-Dist: mock
Requires-Dist: clamd
Provides-Extra: test
Requires-Dist: pytest ; extra == 'test'
Requires-Dist: pytest-platform-markers ; extra == 'test'
